c2qa/__init__.py
c2qa/circuit.py
c2qa/kraus.py
c2qa/operators.py
c2qa/qumoderegister.py
c2qa/stateReadout.py
c2qa/util.py
tests/__init__.py
tests/test_circuit.py
tests/test_gates.py
tests/test_inconsistent_statevectors.py
tests/test_noise_model.py
tests/test_operators.py
tests/test_parameterized.py
tests/test_qiskit.py
tests/test_qumoderegister.py
tests/test_tomography.py
tests/test_util.py
c2qa_qiskit-5.0.1.dist-info/METADATA
c2qa_qiskit-5.0.1.dist-info/WHEEL
c2qa_qiskit-5.0.1.dist-info/top_level.txt
c2qa_qiskit-5.0.1.dist-info/RECORD
